dmpcpwa/__init__.py
dmpcpwa/agents/__init__.py
dmpcpwa/agents/g_admm_coordinator.py
dmpcpwa/agents/mld_agent.py
dmpcpwa/agents/no_control_agent.py
dmpcpwa/agents/pwa_agent.py
dmpcpwa/agents/sqp_admm_coordinator.py
dmpcpwa/mpc/__init__.py
dmpcpwa/mpc/mpc_mld.py
dmpcpwa/mpc/mpc_mld_cent_decup.py
dmpcpwa/mpc/mpc_switching.py
dmpcpwa/utils/__init__.py
dmpcpwa/utils/pwa_models.py
dmpcpwa/utils/tikz.py
dmpcpwa-0.0.3.dist-info/LICENSE
dmpcpwa-0.0.3.dist-info/METADATA
dmpcpwa-0.0.3.dist-info/WHEEL
dmpcpwa-0.0.3.dist-info/top_level.txt
dmpcpwa-0.0.3.dist-info/RECORD
